b7w_cli/__init__.py
b7w_cli/behappy.py
b7w_cli/cli.py
b7w_cli/images.py
b7w_cli/mac.py
b7w_cli/utils.py
b7w_cli/video.py
b7w_cli-0.3.3.dist-info/LICENSE
b7w_cli-0.3.3.dist-info/METADATA
b7w_cli-0.3.3.dist-info/WHEEL
b7w_cli-0.3.3.dist-info/entry_points.txt
b7w_cli-0.3.3.dist-info/RECORD
