Metadata-Version: 2.3
Name: b7w-cli
Version: 0.3.3
Summary: Useful cli for photos and other things
License: MIT
Author: B7W
Author-email: b7w@isudo.ru
Requires-Python: >=3.11,<4.0
Classifier: License :: OSI Approved :: MIT License
Classifier: Programming Language :: Python :: 3
Classifier: Programming Language :: Python :: 3.11
Classifier: Programming Language :: Python :: 3.12
Classifier: Programming Language :: Python :: 3.13
Requires-Dist: click (>=8.1,<9.0)
Requires-Dist: python-dateutil (>=2.9,<3.0)
Requires-Dist: toml (>=0.10.1,<0.11.0)
